Workbook

Sheet Supuestos
A1: MODELO — LOTEO 19,26 HA · AV. SAN MIGUEL 6850, TALCA
A2: Las celdas en rojo son inputs. Todo lo demás se calcula.
A4: DATOS DUROS (planos L_02 / L_03, agosto 2023)
A5: Partida | B5: Valor | C5: Unidad | F5: Fuente
A6: Paño fusionado | B6: 192627 | C6: m² | F6: Cuadro de fusión L_02
A7: Superficie de los 90 sitios | B7: 127866 | C7: m² | F7: Suma cuadro de superficies L_03
A8: N° de sitios | B8: 90 | C8: u | F8: Listado de lotes L_03
A9: Paño colegio | B9: 18619 | C9: m² | F9: L_03
A10: Paño locales comerciales | B10: 4386 | C10: m² | F10: L_03
A11: Áreas verdes | B11: 13798 | C11: m² | F11: 11.649 + 2.149, L_03
A12: Vialidad + expropiación | B12: 27958 | C12: m² | F12: Por diferencia
A13: Superficie promedio por sitio | B13: =B6/B7 | C13: m²
A15: INPUTS — TERRENO
A16: Variable | B16: Valor | C16: Unidad | F16: Comentario
A17: Precio del terreno | B17: 119000 | C17: UF | F17: Precio pedido por el vendedor
A18: Pie | B18: 10000 | C18: UF | F18: Propuesto: 10.000 en vez de 20.000
A19: % de cada venta destinado al terreno | B19: 0.3 | C19: % | F19: 30% de cada escritura
A20: Año de vencimiento del plazo | B20: 6 | C20: año | F20: 5 años desde el permiso, obtenido en el año 1
A21: Saldo contra flujo | B21: =B17-B18 | C21: UF
A23: INPUTS — ESCENARIOS
A24: Variable | B24: Conservador | C24: Base | D24: Optimista | F24: Comentario
A25: Sitios vendidos por año | B25: 10 | C25: 15 | D25: 21 | F25: El supuesto que decide el negocio
A26: Año de inicio de ventas | B26: 3 | C26: 2 | D26: 1 | F26: Depende de permisos y factibilidad
A27: Precio inicial | B27: 3.3 | C27: 3.5 | D27: 3.5 | F27: UF/m²
A28: Precio maduro | B28: 3.8 | C28: 4 | D28: 4.2 | F28: UF/m², desde el año 3 de venta
A29: Año de venta en que sube el precio | B29: 4 | C29: 3 | D29: 2 | F29: 1 = primer año de venta
A30: Urbanización total (IVA incluido) | B30: 80000 | C30: 60000 | D30: 45000 | F30: UF — reconstruido del resumen por km; cotizar en firme
A31: Gasto comercial | B31: 0.055 | C31: 0.045 | D31: 0.04 | F31: % sobre ventas
A32: Administración anual | B32: 3000 | C32: 2500 | D32: 2500 | F32: UF/año
A33: Proyectos y permisos año 0 | B33: 9000 | C33: 9000 | D33: 9000 | F33: UF
A34: Proyectos y permisos año 1 | B34: 5000 | C34: 5000 | D34: 5000 | F34: UF
A35: Contribuciones anuales | B35: 500 | C35: 500 | D35: 500 | F35: UF/año, incluye sobretasa sitio eriazo
A36: Impuesto a la renta | B36: 0.27 | C36: 0.27 | D36: 0.27 | F36: Primera categoría
... A38: Preventa cobrada un año antes | B38: 0.2 | C38: 0.2 | D38: 0.2 | F38: Pie de promesa

Sheet Flujo Conservador
A1: FLUJO DE CAJA — ESCENARIO CONSERVADOR
A2: Todos los valores en UF. Cambiar supuestos en la hoja 'Supuestos'.
A4: Concepto | B4: Año 0 | C4: Año 1 | D4: Año 2 | E4: Año 3 | F4: Año 4 | G4: Año 5 | H4: Año 6 | I4: Año 7 | J4: Año 8 | K4: Año 9 | L4: Año 10 | M4: Año 11 | N4: Año 12 | O4: Año 13 | P4: Año 14 | Q4: Año 15
A5: Año | B5: 0 | C5: 1 | D5: 2 | E5: 3 | F5: 4 | G5: 5 | H5: 6 | I5: 7 | J5: 8 | K5: 9 | L5: 10 | M5: 11 | N5: 12 | O5: 13 | P5: 14 | Q5: 15
A6: Sitios vendidos acumulados (previo) | B6: =0 | C6: =B6+B7 | D6: =C6+C7 | E6: =D6+D7 | F6: =E6+E7 | G6: =F6+F7 | H6: =G6+G7 | I6: =H6+H7 | J6: =I6+I7 | ... Q6: =P6+P7
A7: Sitios vendidos en el año | B7: =IF(0<Supuestos!$B$26,0,MIN(Supuestos!$B$25,Supuestos!$B$7-B6)) | C7: =IF(1<Supuestos!$B$26,0,MIN(Supuestos!$B$25,Supuestos!$B$7-C6)) | D7: =IF(2<Supuestos!$B$26,0,MIN(Supuestos!$B$25,Supuestos!$B$7-D6)) | E7: =IF(3<Supuestos!$B$26,0,MIN(Supuestos!$B$25,Supuestos!$B$7-E6)) | F7: =IF(4<Supuestos!$B$26,0,MIN(Supuestos!$B$25,Supuestos!$B$7-F6)) | G7: =IF(5<Supuestos!$B$26,0,MIN(Supuestos!$B$25,Supuestos!$B$7-G6)) | H7: =IF(6<Supuestos!$B$26,0,MIN(Supuestos!$B$25,Supuestos!$B$7-H6)) | I7: =IF(7<Supuestos!$B$26,0,MIN(Supuestos!$B$25,Supuestos!$B$7-I6)) | J7: =IF(8<Supuestos!$B$26,0,MIN(Supuestos!$B$25,Supuestos!$B$7-J6)) | K7: =IF(9<Supuestos!$B$26,0,MIN(Supuestos!$B$25,Supuestos!$B$7-K6)) | L7: =IF(10<Supuestos!$B$26,0,MIN(Supuestos!$B$25,Supuestos!$B$7-L6)) | M7: =IF(11<Supuestos!$B$26,0,MIN(Supuestos!$B$25,Supuestos!$B$7-M6)) | N7: =IF(12<Supuestos!$B$26,0,MIN(Supuestos!$B$25,Supuestos!$B$7-N6)) | O7: =IF(13<Supuestos!$B$26,0,MIN(Supuestos!$B$25,Supuestos!$B$7-O6)) | P7: =IF(14<Supuestos!$B$26,0,MIN(Supuestos!$B$25,Supuestos!$B$7-P6)) | Q7: =IF(15<Supuestos!$B$26,0,MIN(Supuestos!$B$25,Supuestos!$B$7-Q6))
A8: Precio del año (UF/m²) | B8: =IF(0<Supuestos!$B$26,0,IF(0-Supuestos!$B$26+1>=Supuestos!$B$29,Supuestos!$B$28,Supuestos!$B$27)) | C8: =IF(1<Supuestos!$B$26,0,IF(1-Supuestos!$B$26+1>=Supuestos!$B$29,Supuestos!$B$28,Supuestos!$B$27)) | D8: =IF(2<Supuestos!$B$26,0,IF(2-Supuestos!$B$26+1>=Supuestos!$B$29,Supuestos!$B$28,Supuestos!$B$27)) | E8: =IF(3<Supuestos!$B$26,0,IF(3-Supuestos!$B$26+1>=Supuestos!$B$29,Supuestos!$B$28,Supuestos!$B$27)) | F8: =IF(4<Supuestos!$B$26,0,IF(4-Supuestos!$B$26+1>=Supuestos!$B$29,Supuestos!$B$28,Supuestos!$B$27)) | G8: =IF(5<Supuestos!$B$26,0,IF(5-Supuestos!$B$26+1>=Supuestos!$B$29,Supuestos!$B$28,Supuestos!$B$27)) | H8: =IF(6<Supuestos!$B$26,0,IF(6-Supuestos!$B$26+1>=Supuestos!$B$29,Supuestos!$B$28,Supuestos!$B$27)) | I8: =IF(7<Supuestos!$B$26,0,IF(7-Supuestos!$B$26+1>=Supuestos!$B$29,Supuestos!$B$28,Supuestos!$B$27)) | J8: =IF(8<Supuestos!$B$26,0,IF(8-Supuestos!$B$26+1>=Supuestos!$B$29,Supuestos!$B$28,Supuestos!$B$27)) | K8: =IF(9<Supuestos!$B$26,0,IF(9-Supuestos!$B$26+1>=Supuestos!$B$29,Supuestos!$B$28,Supuestos!$B$27)) | L8: =IF(10<Supuestos!$B$26,0,IF(10-Supuestos!$B$26+1>=Supuestos!$B$29,Supuestos!$B$28,Supuestos!$B$27)) | M8: =IF(11<Supuestos!$B$26,0,IF(11-Supuestos!$B$26+1>=Supuestos!$B$29,Supuestos!$B$28,Supuestos!$B$27)) | N8: =IF(12<Supuestos!$B$26,0,IF(12-Supuestos!$B$26+1>=Supuestos!$B$29,Supuestos!$B$28,Supuestos!$B$27)) | O8: =IF(13<Supuestos!$B$26,0,IF(13-Supuestos!$B$26+1>=Supuestos!$B$29,Supuestos!$B$28,Supuestos!$B$27)) | P8: =IF(14<Supuestos!$B$26,0,IF(14-Supuestos!$B$26+1>=Supuestos!$B$29,Supuestos!$B$28,Supuestos!$B$27)) | Q8: =IF(15<Supuestos!$B$26,0,IF(15-Supuestos!$B$26+1>=Supuestos!$B$29,Supuestos!$B$28,Supuestos!$B$27))
A9: Ingresos por venta | B9: =B7*Supuestos!$B$13*B8 | C9: =C7*Supuestos!$B$13*C8 | D9: =D7*Supuestos!$B$13*D8 | E9: =E7*Supuestos!$B$13*E8 | F9: =F7*Supuestos!$B$13*F8 | G9: =G7*Supuestos!$B$13*G8 | H9: =H7*Supuestos!$B$13*H8 | I9: =I7*Supuestos!$B$13*I8 | ... Q9: =Q7*Supuestos!$B$13*Q8
A10: Caja por ventas (20% anticipado) | B10: =B9*(1-Supuestos!$B$38)+C9*Supuestos!$B$38 | C10: =C9*(1-Supuestos!$B$38)+D9*Supuestos!$B$38 | D10: =D9*(1-Supuestos!$B$38)+E9*Supuestos!$B$38 | E10: =E9*(1-Supuestos!$B$38)+F9*Supuestos!$B$38 | F10: =F9*(1-Supuestos!$B$38)+G9*Supuestos!$B$38 | G10: =G9*(1-Supuestos!$B$38)+H9*Supuestos!$B$38 | H10: =H9*(1-Supuestos!$B$38)+I9*Supuestos!$B$38 | I10: =I9*(1-Supuestos!$B$38)+J9*Supuestos!$B$38 | ... P10: =P9*(1-Supuestos!$B$38)+Q9*Supuestos!$B$38 | Q10: =Q9*(1-Supuestos!$B$38)
A12: Urbanización (4 macro-etapas) | B12: =Supuestos!$B$30*(IF(0=Supuestos!$B$26-1,0.3,0)+IF(0=Supuestos!$B$26,0.25,0)+IF(0=Supuestos!$B$26+2,0.25,0)+IF(0=Supuestos!$B$26+4,0.2,0)) | C12: =Supuestos!$B$30*(IF(1=Supuestos!$B$26-1,0.3,0)+IF(1=Supuestos!$B$26,0.25,0)+IF(1=Supuestos!$B$26+2,0.25,0)+IF(1=Supuestos!$B$26+4,0.2,0)) | D12: =Supuestos!$B$30*(IF(2=Supuestos!$B$26-1,0.3,0)+IF(2=Supuestos!$B$26,0.25,0)+IF(2=Supuestos!$B$26+2,0.25,0)+IF(2=Supuestos!$B$26+4,0.2,0)) | E12: =Supuestos!$B$30*(IF(3=Supuestos!$B$26-1,0.3,0)+IF(3=Supuestos!$B$26,0.25,0)+IF(3=Supuestos!$B$26+2,0.25,0)+IF(3=Supuestos!$B$26+4,0.2,0)) | F12: =Supuestos!$B$30*(IF(4=Supuestos!$B$26-1,0.3,0)+IF(4=Supuestos!$B$26,0.25,0)+IF(4=Supuestos!$B$26+2,0.25,0)+IF(4=Supuestos!$B$26+4,0.2,0)) | G12: =Supuestos!$B$30*(IF(5=Supuestos!$B$26-1,0.3,0)+IF(5=Supuestos!$B$26,0.25,0)+IF(5=Supuestos!$B$26+2,0.25,0)+IF(5=Supuestos!$B$26+4,0.2,0)) | H12: =Supuestos!$B$30*(IF(6=Supuestos!$B$26-1,0.3,0)+IF(6=Supuestos!$B$26,0.25,0)+IF(6=Supuestos!$B$26+2,0.25,0)+IF(6=Supuestos!$B$26+4,0.2,0)) | I12: =Supuestos!$B$30*(IF(7=Supuestos!$B$26-1,0.3,0)+IF(7=Supuestos!$B$26,0.25,0)+IF(7=Supuestos!$B$26+2,0.25,0)+IF(7=Supuestos!$B$26+4,0.2,0)) | J12: =Supuestos!$B$30*(IF(8=Supuestos!$B$26-1,0.3,0)+IF(8=Supuestos!$B$26,0.25,0)+IF(8=Supuestos!$B$26+2,0.25,0)+IF(8=Supuestos!$B$26+4,0.2,0)) | K12: =Supuestos!$B$30*(IF(9=Supuestos!$B$26-1,0.3,0)+IF(9=Supuestos!$B$26,0.25,0)+IF(9=Supuestos!$B$26+2,0.25,0)+IF(9=Supuestos!$B$26+4,0.2,0)) | L12: =Supuestos!$B$30*(IF(10=Supuestos!$B$26-1,0.3,0)+IF(10=Supuestos!$B$26,0.25,0)+IF(10=Supuestos!$B$26+2,0.25,0)+IF(10=Supuestos!$B$26+4,0.2,0)) | M12: =Supuestos!$B$30*(IF(11=Supuestos!$B$26-1,0.3,0)+IF(11=Supuestos!$B$26,0.25,0)+IF(11=Supuestos!$B$26+2,0.25,0)+IF(11=Supuestos!$B$26+4,0.2,0)) | N12: =Supuestos!$B$30*(IF(12=Supuestos!$B$26-1,0.3,0)+IF(12=Supuestos!$B$26,0.25,0)+IF(12=Supuestos!$B$26+2,0.25,0)+IF(12=Supuestos!$B$26+4,0.2,0)) | O12: =Supuestos!$B$30*(IF(13=Supuestos!$B$26-1,0.3,0)+IF(13=Supuestos!$B$26,0.25,0)+IF(13=Supuestos!$B$26+2,0.25,0)+IF(13=Supuestos!$B$26+4,0.2,0)) | P12: =Supuestos!$B$30*(IF(14=Supuestos!$B$26-1,0.3,0)+IF(14=Supuestos!$B$26,0.25,0)+IF(14=Supuestos!$B$26+2,0.25,0)+IF(14=Supuestos!$B$26+4,0.2,0)) | Q12: =Supuestos!$B$30*(IF(15=Supuestos!$B$26-1,0.3,0)+IF(15=Supuestos!$B$26,0.25,0)+IF(15=Supuestos!$B$26+2,0.25,0)+IF(15=Supuestos!$B$26+4,0.2,0))
A13: Proyectos, permisos y especialidades | B13: =Supuestos!$B$33 | C13: =Supuestos!$B$34 | D13: 0 | E13: 0 | F13: 0 | G13: 0 | H13: 0 | I13: 0 | J13: 0 | K13: 0 | L13: 0 | M13: 0 | N13: 0 | O13: 0 | P13: 0 | Q13: 0
A14: Gasto comercial | B14: =B9*Supuestos!$B$31 | C14: =C9*Supuestos!$B$31 | D14: =D9*Supuestos!$B$31 | E14: =E9*Supuestos!$B$31 | F14: =F9*Supuestos!$B$31 | G14: =G9*Supuestos!$B$31 | H14: =H9*Supuestos!$B$31 | I14: =I9*Supuestos!$B$31 | ... Q14: =Q9*Supuestos!$B$31
A15: Administración y contribuciones | B15: =IF(OR(B7>0,0<Supuestos!$B$26),Supuestos!$B$32+Supuestos!$B$35,0) | C15: =IF(OR(C7>0,1<Supuestos!$B$26),Supuestos!$B$32+Supuestos!$B$35,0) | D15: =IF(OR(D7>0,2<Supuestos!$B$26),Supuestos!$B$32+Supuestos!$B$35,0) | E15: =IF(OR(E7>0,3<Supuestos!$B$26),Supuestos!$B$32+Supuestos!$B$35,0) | F15: =IF(OR(F7>0,4<Supuestos!$B$26),Supuestos!$B$32+Supuestos!$B$35,0) | G15: =IF(OR(G7>0,5<Supuestos!$B$26),Supuestos!$B$32+Supuestos!$B$35,0) | H15: =IF(OR(H7>0,6<Supuestos!$B$26),Supuestos!$B$32+Supuestos!$B$35,0) | I15: =IF(OR(I7>0,7<Supuestos!$B$26),Supuestos!$B$32+Supuestos!$B$35,0) | J15: =IF(OR(J7>0,8<Supuestos!$B$26),Supuestos!$B$32+Supuestos!$B$35,0) | K15: =IF(OR(K7>0,9<Supuestos!$B$26),Supuestos!$B$32+Supuestos!$B$35,0) | L15: =IF(OR(L7>0,10<Supuestos!$B$26),Supuestos!$B$32+Supuestos!$B$35,0) | M15: =IF(OR(M7>0,11<Supuestos!$B$26),Supuestos!$B$32+Supuestos!$B$35,0) | N15: =IF(OR(N7>0,12<Supuestos!$B$26),Supuestos!$B$32+Supuestos!$B$35,0) | O15: =IF(OR(O7>0,13<Supuestos!$B$26),Supuestos!$B$32+Supuestos!$B$35,0) | P15: =IF(OR(P7>0,14<Supuestos!$B$26),Supuestos!$B$32+Supuestos!$B$35,0) | Q15: =IF(OR(Q7>0,15<Supuestos!$B$26),Supuestos!$B$32+Supuestos!$B$35,0)
A16: Total egresos operacionales | B16: =B12+B13+B14+B15 | C16: =C12+C13+C14+C15 | D16: =D12+D13+D14+D15 | E16: =E12+E13+E14+E15 | F16: =F12+F13+F14+F15 | G16: =G12+G13+G14+G15 | H16: =H12+H13+H14+H15 | I16: =I12+I13+I14+I15 | ... Q16: =Q12+Q13+Q14+Q15
A18: Pago del terreno | B18: =Supuestos!$B$18 | C18: =IF(1>=Supuestos!$B$20,MAX(0,Supuestos!$B$17-SUM($B18:B18)),MIN(C10*Supuestos!$B$19,MAX(0,Supuestos!$B$17-SUM($B18:B18)))) | D18: =IF(2>=Supuestos!$B$20,MAX(0,Supuestos!$B$17-SUM($B18:C18)),MIN(D10*Supuestos!$B$19,MAX(0,Supuestos!$B$17-SUM($B18:C18)))) | E18: =IF(3>=Supuestos!$B$20,MAX(0,Supuestos!$B$17-SUM($B18:D18)),MIN(E10*Supuestos!$B$19,MAX(0,Supuestos!$B$17-SUM($B18:D18)))) | F18: =IF(4>=Supuestos!$B$20,MAX(0,Supuestos!$B$17-SUM($B18:E18)),MIN(F10*Supuestos!$B$19,MAX(0,Supuestos!$B$17-SUM($B18:E18)))) | G18: =IF(5>=Supuestos!$B$20,MAX(0,Supuestos!$B$17-SUM($B18:F18)),MIN(G10*Supuestos!$B$19,MAX(0,Supuestos!$B$17-SUM($B18:F18)))) | H18: =IF(6>=Supuestos!$B$20,MAX(0,Supuestos!$B$17-SUM($B18:G18)),MIN(H10*Supuestos!$B$19,MAX(0,Supuestos!$B$17-SUM($B18:G18)))) | I18: =IF(7>=Supuestos!$B$20,MAX(0,Supuestos!$B$17-SUM($B18:H18)),MIN(I10*Supuestos!$B$19,MAX(0,Supuestos!$B$17-SUM($B18:H18)))) | J18: =IF(8>=Supuestos!$B$20,MAX(0,Supuestos!$B$17-SUM($B18:I18)),MIN(J10*Supuestos!$B$19,MAX(0,Supuestos!$B$17-SUM($B18:I18)))) | K18: =IF(9>=Supuestos!$B$20,MAX(0,Supuestos!$B$17-SUM($B18:J18)),MIN(K10*Supuestos!$B$19,MAX(0,Supuestos!$B$17-SUM($B18:J18)))) | L18: =IF(10>=Supuestos!$B$20,MAX(0,Supuestos!$B$17-SUM($B18:K18)),MIN(L10*Supuestos!$B$19,MAX(0,Supuestos!$B$17-SUM($B18:K18)))) | M18: =IF(11>=Supuestos!$B$20,MAX(0,Supuestos!$B$17-SUM($B18:L18)),MIN(M10*Supuestos!$B$19,MAX(0,Supuestos!$B$17-SUM($B18:L18)))) | N18: =IF(12>=Supuestos!$B$20,MAX(0,Supuestos!$B$17-SUM($B18:M18)),MIN(N10*Supuestos!$B$19,MAX(0,Supuestos!$B$17-SUM($B18:M18)))) | O18: =IF(13>=Supuestos!$B$20,MAX(0,Supuestos!$B$17-SUM($B18:N18)),MIN(O10*Supuestos!$B$19,MAX(0,Supuestos!$B$17-SUM($B18:N18)))) | P18: =IF(14>=Supuestos!$B$20,MAX(0,Supuestos!$B$17-SUM($B18:O18)),MIN(P10*Supuestos!$B$19,MAX(0,Supuestos!$B$17-SUM($B18:O18)))) | Q18: =IF(15>=Supuestos!$B$20,MAX(0,Supuestos!$B$17-SUM($B18:P18)),MIN(Q10*Supuestos!$B$19,MAX(0,Supuestos!$B$17-SUM($B18:P18))))
A19: Saldo del terreno pendiente | B19: =MAX(0,Supuestos!$B$17-SUM($B18:B18)) | C19: =MAX(0,Supuestos!$B$17-SUM($B18:C18)) | D19: =MAX(0,Supuestos!$B$17-SUM($B18:D18)) | E19: =MAX(0,Supuestos!$B$17-SUM($B18:E18)) | F19: =MAX(0,Supuestos!$B$17-SUM($B18:F18)) | G19: =MAX(0,Supuestos!$B$17-SUM($B18:G18)) | H19: =MAX(0,Supuestos!$B$17-SUM($B18:H18)) | I19: =MAX(0,Supuestos!$B$17-SUM($B18:I18)) | ... Q19: =MAX(0,Supuestos!$B$17-SUM($B18:Q18))
A20: Impuesto a la renta (pagado al año siguiente) | B20: 0 | C20: =MAX(0,(B9-B16-B7*Supuestos!$B$17*0.881/Supuestos!$B$7)*Supuestos!$B$36) | D20: =MAX(0,(C9-C16-C7*Supuestos!$B$17*0.881/Supuestos!$B$7)*Supuestos!$B$36) | E20: =MAX(0,(D9-D16-D7*Supuestos!$B$17*0.881/Supuestos!$B$7)*Supuestos!$B$36) | F20: =MAX(0,(E9-E16-E7*Supuestos!$B$17*0.881/Supuestos!$B$7)*Supuestos!$B$36) | G20: =MAX(0,(F9-F16-F7*Supuestos!$B$17*0.881/Supuestos!$B$7)*Supuestos!$B$36) | H20: =MAX(0,(G9-G16-G7*Supuestos!$B$17*0.881/Supuestos!$B$7)*Supuestos!$B$36) | I20: =MAX(0,(H9-H16-H7*Supuestos!$B$17*0.881/Supuestos!$B$7)*Supuestos!$B$36) | J20: =MAX(0,(I9-I16-I7*Supuestos!$B$17*0.881/Supuestos!$B$7)*Supuestos!$B$36) | ... Q20: =MAX(0,(P9-P16-P7*Supuestos!$B$17*0.881/Supuestos!$B$7)*Supuestos!$B$36)
A22: FLUJO DE CAJA DEL PERÍODO | B22: =B10-B16-B18-B20 | C22: =C10-C16-C18-C20 | D22: =D10-D16-D18-D20 | E22: =E10-E16-E18-E20 | F22: =F10-F16-F18-F20 | G22: =G10-G16-G18-G20 | H22: =H10-H16-H18-H20 | I22: =I10-I16-I18-I20 | ... Q22: =Q10-Q16-Q18-Q20
A23: Flujo acumulado | B23: =B22 | C23: =B23+C22 | D23: =C23+D22 | E23: =D23+E22 | F23: =E23+F22 | G23: =F23+G22 | H23: =G23+H22 | I23: =H23+I22 | J23: =I23+J22 | ... Q23: =P23+Q22
A25: INDICADORES
A26: Ingresos totales | B26: =SUM(B9:Q9)
A27: Costos totales (con terreno) | B27: =SUM(B16:Q16)+Supuestos!$B$17*0.881
A28: Utilidad antes de impuesto | B28: =B26-B27
A29: Margen bruto | B29: =B28/B26
A30: Impuesto | B30: =B28*Supuestos!$B$36
A31: Utilidad neta | B31: =B28-B30
A32: Margen neto | B32: =B31/B26
A33: Capital máximo expuesto | B33: =-MIN(B23:Q23,0)
A34: TIR del proyecto | B34: =IRR(B22:Q22)
A35: VAN a la tasa de descuento | B35: =NPV(Supuestos!$B$37,C22:Q22)+B22
A36: Precio promedio logrado (UF/m²) | B36: =B26/Supuestos!$B$6
A37: Saldo impago al vencer el plazo | B37: =INDEX(B19:Q19,Supuestos!$B$20+1)

Sheet Flujo Base
A1: FLUJO DE CAJA — ESCENARIO BASE
A2: Todos los valores en UF. Cambiar supuestos en la hoja 'Supuestos'.
A4: Concepto | B4: Año 0 | C4: Año 1 | D4: Año 2 | E4: Año 3 | F4: Año 4 | G4: Año 5 | H4: Año 6 | I4: Año 7 | J4: Año 8 | K4: Año 9 | L4: Año 10 | M4: Año 11 | N4: Año 12 | O4: Año 13 | P4: Año 14 | Q4: Año 15
A5: Año | B5: 0 | C5: 1 | D5: 2 | E5: 3 | F5: 4 | G5: 5 | H5: 6 | I5: 7 | J5: 8 | K5: 9 | L5: 10 | M5: 11 | N5: 12 | O5: 13 | P5: 14 | Q5: 15
A6: Sitios vendidos acumulados (previo) | B6: =0 | C6: =B6+B7 | D6: =C6+C7 | E6: =D6+D7 | F6: =E6+E7 | G6: =F6+F7 | H6: =G6+G7 | I6: =H6+H7 | J6: =I6+I7 | ... Q6: =P6+P7
A7: Sitios vendidos en el año | B7: =IF(0<Supuestos!$C$26,0,MIN(Supuestos!$C$25,Supuestos!$B$7-B6)) | C7: =IF(1<Supuestos!$C$26,0,MIN(Supuestos!$C$25,Supuestos!$B$7-C6)) | D7: =IF(2<Supuestos!$C$26,0,MIN(Supuestos!$C$25,Supuestos!$B$7-D6)) | E7: =IF(3<Supuestos!$C$26,0,MIN(Supuestos!$C$25,Supuestos!$B$7-E6)) | F7: =IF(4<Supuestos!$C$26,0,MIN(Supuestos!$C$25,Supuestos!$B$7-F6)) | G7: =IF(5<Supuestos!$C$26,0,MIN(Supuestos!$C$25,Supuestos!$B$7-G6)) | H7: =IF(6<Supuestos!$C$26,0,MIN(Supuestos!$C$25,Supuestos!$B$7-H6)) | I7: =IF(7<Supuestos!$C$26,0,MIN(Supuestos!$C$25,Supuestos!$B$7-I6)) | J7: =IF(8<Supuestos!$C$26,0,MIN(Supuestos!$C$25,Supuestos!$B$7-J6)) | K7: =IF(9<Supuestos!$C$26,0,MIN(Supuestos!$C$25,Supuestos!$B$7-K6)) | L7: =IF(10<Supuestos!$C$26,0,MIN(Supuestos!$C$25,Supuestos!$B$7-L6)) | M7: =IF(11<Supuestos!$C$26,0,MIN(Supuestos!$C$25,Supuestos!$B$7-M6)) | N7: =IF(12<Supuestos!$C$26,0,MIN(Supuestos!$C$25,Supuestos!$B$7-N6)) | O7: =IF(13<Supuestos!$C$26,0,MIN(Supuestos!$C$25,Supuestos!$B$7-O6)) | P7: =IF(14<Supuestos!$C$26,0,MIN(Supuestos!$C$25,Supuestos!$B$7-P6)) | Q7: =IF(15<Supuestos!$C$26,0,MIN(Supuestos!$C$25,Supuestos!$B$7-Q6))
A8: Precio del año (UF/m²) | B8: =IF(0<Supuestos!$C$26,0,IF(0-Supuestos!$C$26+1>=Supuestos!$C$29,Supuestos!$C$28,Supuestos!$C$27)) | C8: =IF(1<Supuestos!$C$26,0,IF(1-Supuestos!$C$26+1>=Supuestos!$C$29,Supuestos!$C$28,Supuestos!$C$27)) | D8: =IF(2<Supuestos!$C$26,0,IF(2-Supuestos!$C$26+1>=Supuestos!$C$29,Supuestos!$C$28,Supuestos!$C$27)) | E8: =IF(3<Supuestos!$C$26,0,IF(3-Supuestos!$C$26+1>=Supuestos!$C$29,Supuestos!$C$28,Supuestos!$C$27)) | F8: =IF(4<Supuestos!$C$26,0,IF(4-Supuestos!$C$26+1>=Supuestos!$C$29,Supuestos!$C$28,Supuestos!$C$27)) | G8: =IF(5<Supuestos!$C$26,0,IF(5-Supuestos!$C$26+1>=Supuestos!$C$29,Supuestos!$C$28,Supuestos!$C$27)) | H8: =IF(6<Supuestos!$C$26,0,IF(6-Supuestos!$C$26+1>=Supuestos!$C$29,Supuestos!$C$28,Supuestos!$C$27)) | I8: =IF(7<Supuestos!$C$26,0,IF(7-Supuestos!$C$26+1>=Supuestos!$C$29,Supuestos!$C$28,Supuestos!$C$27)) | J8: =IF(8<Supuestos!$C$26,0,IF(8-Supuestos!$C$26+1>=Supuestos!$C$29,Supuestos!$C$28,Supuestos!$C$27)) | K8: =IF(9<Supuestos!$C$26,0,IF(9-Supuestos!$C$26+1>=Supuestos!$C$29,Supuestos!$C$28,Supuestos!$C$27)) | L8: =IF(10<Supuestos!$C$26,0,IF(10-Supuestos!$C$26+1>=Supuestos!$C$29,Supuestos!$C$28,Supuestos!$C$27)) | M8: =IF(11<Supuestos!$C$26,0,IF(11-Supuestos!$C$26+1>=Supuestos!$C$29,Supuestos!$C$28,Supuestos!$C$27)) | N8: =IF(12<Supuestos!$C$26,0,IF(12-Supuestos!$C$26+1>=Supuestos!$C$29,Supuestos!$C$28,Supuestos!$C$27)) | O8: =IF(13<Supuestos!$C$26,0,IF(13-Supuestos!$C$26+1>=Supuestos!$C$29,Supuestos!$C$28,Supuestos!$C$27)) | P8: =IF(14<Supuestos!$C$26,0,IF(14-Supuestos!$C$26+1>=Supuestos!$C$29,Supuestos!$C$28,Supuestos!$C$27)) | Q8: =IF(15<Supuestos!$C$26,0,IF(15-Supuestos!$C$26+1>=Supuestos!$C$29,Supuestos!$C$28,Supuestos!$C$27))
A9: Ingresos por venta | B9: =B7*Supuestos!$B$13*B8 | C9: =C7*Supuestos!$B$13*C8 | D9: =D7*Supuestos!$B$13*D8 | E9: =E7*Supuestos!$B$13*E8 | F9: =F7*Supuestos!$B$13*F8 | G9: =G7*Supuestos!$B$13*G8 | H9: =H7*Supuestos!$B$13*H8 | I9: =I7*Supuestos!$B$13*I8 | ... Q9: =Q7*Supuestos!$B$13*Q8
A10: Caja por ventas (20% anticipado) | B10: =B9*(1-Supuestos!$C$38)+C9*Supuestos!$C$38 | C10: =C9*(1-Supuestos!$C$38)+D9*Supuestos!$C$38 | D10: =D9*(1-Supuestos!$C$38)+E9*Supuestos!$C$38 | E10: =E9*(1-Supuestos!$C$38)+F9*Supuestos!$C$38 | F10: =F9*(1-Supuestos!$C$38)+G9*Supuestos!$C$38 | G10: =G9*(1-Supuestos!$C$38)+H9*Supuestos!$C$38 | H10: =H9*(1-Supuestos!$C$38)+I9*Supuestos!$C$38 | I10: =I9*(1-Supuestos!$C$38)+J9*Supuestos!$C$38 | ... P10: =P9*(1-Supuestos!$C$38)+Q9*Supuestos!$C$38 | Q10: =Q9*(1-Supuestos!$C$38)
A12: Urbanización (4 macro-etapas) | B12: =Supuestos!$C$30*(IF(0=Supuestos!$C$26-1,0.3,0)+IF(0=Supuestos!$C$26,0.25,0)+IF(0=Supuestos!$C$26+2,0.25,0)+IF(0=Supuestos!$C$26+4,0.2,0)) | C12: =Supuestos!$C$30*(IF(1=Supuestos!$C$26-1,0.3,0)+IF(1=Supuestos!$C$26,0.25,0)+IF(1=Supuestos!$C$26+2,0.25,0)+IF(1=Supuestos!$C$26+4,0.2,0)) | D12: =Supuestos!$C$30*(IF(2=Supuestos!$C$26-1,0.3,0)+IF(2=Supuestos!$C$26,0.25,0)+IF(2=Supuestos!$C$26+2,0.25,0)+IF(2=Supuestos!$C$26+4,0.2,0)) | E12: =Supuestos!$C$30*(IF(3=Supuestos!$C$26-1,0.3,0)+IF(3=Supuestos!$C$26,0.25,0)+IF(3=Supuestos!$C$26+2,0.25,0)+IF(3=Supuestos!$C$26+4,0.2,0)) | F12: =Supuestos!$C$30*(IF(4=Supuestos!$C$26-1,0.3,0)+IF(4=Supuestos!$C$26,0.25,0)+IF(4=Supuestos!$C$26+2,0.25,0)+IF(4=Supuestos!$C$26+4,0.2,0)) | G12: =Supuestos!$C$30*(IF(5=Supuestos!$C$26-1,0.3,0)+IF(5=Supuestos!$C$26,0.25,0)+IF(5=Supuestos!$C$26+2,0.25,0)+IF(5=Supuestos!$C$26+4,0.2,0)) | H12: =Supuestos!$C$30*(IF(6=Supuestos!$C$26-1,0.3,0)+IF(6=Supuestos!$C$26,0.25,0)+IF(6=Supuestos!$C$26+2,0.25,0)+IF(6=Supuestos!$C$26+4,0.2,0)) | I12: =Supuestos!$C$30*(IF(7=Supuestos!$C$26-1,0.3,0)+IF(7=Supuestos!$C$26,0.25,0)+IF(7=Supuestos!$C$26+2,0.25,0)+IF(7=Supuestos!$C$26+4,0.2,0)) | J12: =Supuestos!$C$30*(IF(8=Supuestos!$C$26-1,0.3,0)+IF(8=Supuestos!$C$26,0.25,0)+IF(8=Supuestos!$C$26+2,0.25,0)+IF(8=Supuestos!$C$26+4,0.2,0)) | K12: =Supuestos!$C$30*(IF(9=Supuestos!$C$26-1,0.3,0)+IF(9=Supuestos!$C$26,0.25,0)+IF(9=Supuestos!$C$26+2,0.25,0)+IF(9=Supuestos!$C$26+4,0.2,0)) | L12: =Supuestos!$C$30*(IF(10=Supuestos!$C$26-1,0.3,0)+IF(10=Supuestos!$C$26,0.25,0)+IF(10=Supuestos!$C$26+2,0.25,0)+IF(10=Supuestos!$C$26+4,0.2,0)) | M12: =Supuestos!$C$30*(IF(11=Supuestos!$C$26-1,0.3,0)+IF(11=Supuestos!$C$26,0.25,0)+IF(11=Supuestos!$C$26+2,0.25,0)+IF(11=Supuestos!$C$26+4,0.2,0)) | N12: =Supuestos!$C$30*(IF(12=Supuestos!$C$26-1,0.3,0)+IF(12=Supuestos!$C$26,0.25,0)+IF(12=Supuestos!$C$26+2,0.25,0)+IF(12=Supuestos!$C$26+4,0.2,0)) | O12: =Supuestos!$C$30*(IF(13=Supuestos!$C$26-1,0.3,0)+IF(13=Supuestos!$C$26,0.25,0)+IF(13=Supuestos!$C$26+2,0.25,0)+IF(13=Supuestos!$C$26+4,0.2,0)) | P12: =Supuestos!$C$30*(IF(14=Supuestos!$C$26-1,0.3,0)+IF(14=Supuestos!$C$26,0.25,0)+IF(14=Supuestos!$C$26+2,0.25,0)+IF(14=Supuestos!$C$26+4,0.2,0)) | Q12: =Supuestos!$C$30*(IF(15=Supuestos!$C$26-1,0.3,0)+IF(15=Supuestos!$C$26,0.25,0)+IF(15=Supuestos!$C$26+2,0.25,0)+IF(15=Supuestos!$C$26+4,0.2,0))
A13: Proyectos, permisos y especialidades | B13: =Supuestos!$C$33 | C13: =Supuestos!$C$34 | D13: 0 | E13: 0 | F13: 0 | G13: 0 | H13: 0 | I13: 0 | J13: 0 | K13: 0 | L13: 0 | M13: 0 | N13: 0 | O13: 0 | P13: 0 | Q13: 0
A14: Gasto comercial | B14: =B9*Supuestos!$C$31 | C14: =C9*Supuestos!$C$31 | D14: =D9*Supuestos!$C$31 | E14: =E9*Supuestos!$C$31 | F14: =F9*Supuestos!$C$31 | G14: =G9*Supuestos!$C$31 | H14: =H9*Supuestos!$C$31 | I14: =I9*Supuestos!$C$31 | ... Q14: =Q9*Supuestos!$C$31
A15: Administración y contribuciones | B15: =IF(OR(B7>0,0<Supuestos!$C$26),Supuestos!$C$32+Supuestos!$C$35,0) | C15: =IF(OR(C7>0,1<Supuestos!$C$26),Supuestos!$C$32+Supuestos!$C$35,0) | D15: =IF(OR(D7>0,2<Supuestos!$C$26),Supuestos!$C$32+Supuestos!$C$35,0) | E15: =IF(OR(E7>0,3<Supuestos!$C$26),Supuestos!$C$32+Supuestos!$C$35,0) | F15: =IF(OR(F7>0,4<Supuestos!$C$26),Supuestos!$C$32+Supuestos!$C$35,0) | G15: =IF(OR(G7>0,5<Supuestos!$C$26),Supuestos!$C$32+Supuestos!$C$35,0) | H15: =IF(OR(H7>0,6<Supuestos!$C$26),Supuestos!$C$32+Supuestos!$C$35,0) | I15: =IF(OR(I7>0,7<Supuestos!$C$26),Supuestos!$C$32+Supuestos!$C$35,0) | J15: =IF(OR(J7>0,8<Supuestos!$C$26),Supuestos!$C$32+Supuestos!$C$35,0) | K15: =IF(OR(K7>0,9<Supuestos!$C$26),Supuestos!$C$32+Supuestos!$C$35,0) | L15: =IF(OR(L7>0,10<Supuestos!$C$26),Supuestos!$C$32+Supuestos!$C$35,0) | M15: =IF(OR(M7>0,11<Supuestos!$C$26),Supuestos!$C$32+Supuestos!$C$35,0) | N15: =IF(OR(N7>0,12<Supuestos!$C$26),Supuestos!$C$32+Supuestos!$C$35,0) | O15: =IF(OR(O7>0,13<Supuestos!$C$26),Supuestos!$C$32+Supuestos!$C$35,0) | P15: =IF(OR(P7>0,14<Supuestos!$C$26),Supuestos!$C$32+Supuestos!$C$35,0) | Q15: =IF(OR(Q7>0,15<Supuestos!$C$26),Supuestos!$C$32+Supuestos!$C$35,0)
A16: Total egresos operacionales | B16: =B12+B13+B14+B15 | C16: =C12+C13+C14+C15 | D16: =D12+D13+D14+D15 | E16: =E12+E13+E14+E15 | F16: =F12+F13+F14+F15 | G16: =G12+G13+G14+G15 | H16: =H12+H13+H14+H15 | I16: =I12+I13+I14+I15 | ... Q16: =Q12+Q13+Q14+Q15
A18: Pago del terreno | B18: =Supuestos!$B$18 | C18: =IF(1>=Supuestos!$B$20,MAX(0,Supuestos!$B$17-SUM($B18:B18)),MIN(C10*Supuestos!$B$19,MAX(0,Supuestos!$B$17-SUM($B18:B18)))) | D18: =IF(2>=Supuestos!$B$20,MAX(0,Supuestos!$B$17-SUM($B18:C18)),MIN(D10*Supuestos!$B$19,MAX(0,Supuestos!$B$17-SUM($B18:C18)))) | E18: =IF(3>=Supuestos!$B$20,MAX(0,Supuestos!$B$17-SUM($B18:D18)),MIN(E10*Supuestos!$B$19,MAX(0,Supuestos!$B$17-SUM($B18:D18)))) | F18: =IF(4>=Supuestos!$B$20,MAX(0,Supuestos!$B$17-SUM($B18:E18)),MIN(F10*Supuestos!$B$19,MAX(0,Supuestos!$B$17-SUM($B18:E18)))) | G18: =IF(5>=Supuestos!$B$20,MAX(0,Supuestos!$B$17-SUM($B18:F18)),MIN(G10*Supuestos!$B$19,MAX(0,Supuestos!$B$17-SUM($B18:F18)))) | H18: =IF(6>=Supuestos!$B$20,MAX(0,Supuestos!$B$17-SUM($B18:G18)),MIN(H10*Supuestos!$B$19,MAX(0,Supuestos!$B$17-SUM($B18:G18)))) | I18: =IF(7>=Supuestos!$B$20,MAX(0,Supuestos!$B$17-SUM($B18:H18)),MIN(I10*Supuestos!$B$19,MAX(0,Supuestos!$B$17-SUM($B18:H18)))) | J18: =IF(8>=Supuestos!$B$20,MAX(0,Supuestos!$B$17-SUM($B18:I18)),MIN(J10*Supuestos!$B$19,MAX(0,Supuestos!$B$17-SUM($B18:I18)))) | K18: =IF(9>=Supuestos!$B$20,MAX(0,Supuestos!$B$17-SUM($B18:J18)),MIN(K10*Supuestos!$B$19,MAX(0,Supuestos!$B$17-SUM($B18:J18)))) | L18: =IF(10>=Supuestos!$B$20,MAX(0,Supuestos!$B$17-SUM($B18:K18)),MIN(L10*Supuestos!$B$19,MAX(0,Supuestos!$B$17-SUM($B18:K18)))) | M18: =IF(11>=Supuestos!$B$20,MAX(0,Supuestos!$B$17-SUM($B18:L18)),MIN(M10*Supuestos!$B$19,MAX(0,Supuestos!$B$17-SUM($B18:L18)))) | N18: =IF(12>=Supuestos!$B$20,MAX(0,Supuestos!$B$17-SUM($B18:M18)),MIN(N10*Supuestos!$B$19,MAX(0,Supuestos!$B$17-SUM($B18:M18)))) | O18: =IF(13>=Supuestos!$B$20,MAX(0,Supuestos!$B$17-SUM($B18:N18)),MIN(O10*Supuestos!$B$19,MAX(0,Supuestos!$B$17-SUM($B18:N18)))) | P18: =IF(14>=Supuestos!$B$20,MAX(0,Supuestos!$B$17-SUM($B18:O18)),MIN(P10*Supuestos!$B$19,MAX(0,Supuestos!$B$17-SUM($B18:O18)))) | Q18: =IF(15>=Supuestos!$B$20,MAX(0,Supuestos!$B$17-SUM($B18:P18)),MIN(Q10*Supuestos!$B$19,MAX(0,Supuestos!$B$17-SUM($B18:P18))))
A19: Saldo del terreno pendiente | B19: =MAX(0,Supuestos!$B$17-SUM($B18:B18)) | C19: =MAX(0,Supuestos!$B$17-SUM($B18:C18)) | D19: =MAX(0,Supuestos!$B$17-SUM($B18:D18)) | E19: =MAX(0,Supuestos!$B$17-SUM($B18:E18)) | F19: =MAX(0,Supuestos!$B$17-SUM($B18:F18)) | G19: =MAX(0,Supuestos!$B$17-SUM($B18:G18)) | H19: =MAX(0,Supuestos!$B$17-SUM($B18:H18)) | I19: =MAX(0,Supuestos!$B$17-SUM($B18:I18)) | ... Q19: =MAX(0,Supuestos!$B$17-SUM($B18:Q18))
A20: Impuesto a la renta (pagado al año siguiente) | B20: 0 | C20: =MAX(0,(B9-B16-B7*Supuestos!$B$17*0.881/Supuestos!$B$7)*Supuestos!$C$36) | D20: =MAX(0,(C9-C16-C7*Supuestos!$B$17*0.881/Supuestos!$B$7)*Supuestos!$C$36) | E20: =MAX(0,(D9-D16-D7*Supuestos!$B$17*0.881/Supuestos!$B$7)*Supuestos!$C$36) | F20: =MAX(0,(E9-E16-E7*Supuestos!$B$17*0.881/Supuestos!$B$7)*Supuestos!$C$36) | G20: =MAX(0,(F9-F16-F7*Supuestos!$B$17*0.881/Supuestos!$B$7)*Supuestos!$C$36) | H20: =MAX(0,(G9-G16-G7*Supuestos!$B$17*0.881/Supuestos!$B$7)*Supuestos!$C$36) | I20: =MAX(0,(H9-H16-H7*Supuestos!$B$17*0.881/Supuestos!$B$7)*Supuestos!$C$36) | J20: =MAX(0,(I9-I16-I7*Supuestos!$B$17*0.881/Supuestos!$B$7)*Supuestos!$C$36) | ... Q20: =MAX(0,(P9-P16-P7*Supuestos!$B$17*0.881/Supuestos!$B$7)*Supuestos!$C$36)
A22: FLUJO DE CAJA DEL PERÍODO | B22: =B10-B16-B18-B20 | C22: =C10-C16-C18-C20 | D22: =D10-D16-D18-D20 | E22: =E10-E16-E18-E20 | F22: =F10-F16-F18-F20 | G22: =G10-G16-G18-G20 | H22: =H10-H16-H18-H20 | I22: =I10-I16-I18-I20 | ... Q22: =Q10-Q16-Q18-Q20
A23: Flujo acumulado | B23: =B22 | C23: =B23+C22 | D23: =C23+D22 | E23: =D23+E22 | F23: =E23+F22 | G23: =F23+G22 | H23: =G23+H22 | I23: =H23+I22 | J23: =I23+J22 | ... Q23: =P23+Q22
A25: INDICADORES
A26: Ingresos totales | B26: =SUM(B9:Q9)
A27: Costos totales (con terreno) | B27: =SUM(B16:Q16)+Supuestos!$B$17*0.881
A28: Utilidad antes de impuesto | B28: =B26-B27
A29: Margen bruto | B29: =B28/B26
A30: Impuesto | B30: =B28*Supuestos!$C$36
A31: Utilidad neta | B31: =B28-B30
A32: Margen neto | B32: =B31/B26
A33: Capital máximo expuesto | B33: =-MIN(B23:Q23,0)
A34: TIR del proyecto | B34: =IRR(B22:Q22)
A35: VAN a la tasa de descuento | B35: =NPV(Supuestos!$C$37,C22:Q22)+B22
A36: Precio promedio logrado (UF/m²) | B36: =B26/Supuestos!$B$6
A37: Saldo impago al vencer el plazo | B37: =INDEX(B19:Q19,Supuestos!$B$20+1)

Sheet Flujo Optimista
A1: FLUJO DE CAJA — ESCENARIO OPTIMISTA
A2: Todos los valores en UF. Cambiar supuestos en la hoja 'Supuestos'.
A4: Concepto | B4: Año 0 | C4: Año 1 | D4: Año 2 | E4: Año 3 | F4: Año 4 | G4: Año 5 | H4: Año 6 | I4: Año 7 | J4: Año 8 | K4: Año 9 | L4: Año 10 | M4: Año 11 | N4: Año 12 | O4: Año 13 | P4: Año 14 | Q4: Año 15
A5: Año | B5: 0 | C5: 1 | D5: 2 | E5: 3 | F5: 4 | G5: 5 | H5: 6 | I5: 7 | J5: 8 | K5: 9 | L5: 10 | M5: 11 | N5: 12 | O5: 13 | P5: 14 | Q5: 15
A6: Sitios vendidos acumulados (previo) | B6: =0 | C6: =B6+B7 | D6: =C6+C7 | E6: =D6+D7 | F6: =E6+E7 | G6: =F6+F7 | H6: =G6+G7 | I6: =H6+H7 | J6: =I6+I7 | ... Q6: =P6+P7
A7: Sitios vendidos en el año | B7: =IF(0<Supuestos!$D$26,0,MIN(Supuestos!$D$25,Supuestos!$B$7-B6)) | C7: =IF(1<Supuestos!$D$26,0,MIN(Supuestos!$D$25,Supuestos!$B$7-C6)) | D7: =IF(2<Supuestos!$D$26,0,MIN(Supuestos!$D$25,Supuestos!$B$7-D6)) | E7: =IF(3<Supuestos!$D$26,0,MIN(Supuestos!$D$25,Supuestos!$B$7-E6)) | F7: =IF(4<Supuestos!$D$26,0,MIN(Supuestos!$D$25,Supuestos!$B$7-F6)) | G7: =IF(5<Supuestos!$D$26,0,MIN(Supuestos!$D$25,Supuestos!$B$7-G6)) | H7: =IF(6<Supuestos!$D$26,0,MIN(Supuestos!$D$25,Supuestos!$B$7-H6)) | I7: =IF(7<Supuestos!$D$26,0,MIN(Supuestos!$D$25,Supuestos!$B$7-I6)) | J7: =IF(8<Supuestos!$D$26,0,MIN(Supuestos!$D$25,Supuestos!$B$7-J6)) | K7: =IF(9<Supuestos!$D$26,0,MIN(Supuestos!$D$25,Supuestos!$B$7-K6)) | L7: =IF(10<Supuestos!$D$26,0,MIN(Supuestos!$D$25,Supuestos!$B$7-L6)) | M7: =IF(11<Supuestos!$D$26,0,MIN(Supuestos!$D$25,Supuestos!$B$7-M6)) | N7: =IF(12<Supuestos!$D$26,0,MIN(Supuestos!$D$25,Supuestos!$B$7-N6)) | O7: =IF(13<Supuestos!$D$26,0,MIN(Supuestos!$D$25,Supuestos!$B$7-O6)) | P7: =IF(14<Supuestos!$D$26,0,MIN(Supuestos!$D$25,Supuestos!$B$7-P6)) | Q7: =IF(15<Supuestos!$D$26,0,MIN(Supuestos!$D$25,Supuestos!$B$7-Q6))
A8: Precio del año (UF/m²) | B8: =IF(0<Supuestos!$D$26,0,IF(0-Supuestos!$D$26+1>=Supuestos!$D$29,Supuestos!$D$28,Supuestos!$D$27)) | C8: =IF(1<Supuestos!$D$26,0,IF(1-Supuestos!$D$26+1>=Supuestos!$D$29,Supuestos!$D$28,Supuestos!$D$27)) | D8: =IF(2<Supuestos!$D$26,0,IF(2-Supuestos!$D$26+1>=Supuestos!$D$29,Supuestos!$D$28,Supuestos!$D$27)) | E8: =IF(3<Supuestos!$D$26,0,IF(3-Supuestos!$D$26+1>=Supuestos!$D$29,Supuestos!$D$28,Supuestos!$D$27)) | F8: =IF(4<Supuestos!$D$26,0,IF(4-Supuestos!$D$26+1>=Supuestos!$D$29,Supuestos!$D$28,Supuestos!$D$27)) | G8: =IF(5<Supuestos!$D$26,0,IF(5-Supuestos!$D$26+1>=Supuestos!$D$29,Supuestos!$D$28,Supuestos!$D$27)) | H8: =IF(6<Supuestos!$D$26,0,IF(6-Supuestos!$D$26+1>=Supuestos!$D$29,Supuestos!$D$28,Supuestos!$D$27)) | I8: =IF(7<Supuestos!$D$26,0,IF(7-Supuestos!$D$26+1>=Supuestos!$D$29,Supuestos!$D$28,Supuestos!$D$27)) | J8: =IF(8<Supuestos!$D$26,0,IF(8-Supuestos!$D$26+1>=Supuestos!$D$29,Supuestos!$D$28,Supuestos!$D$27)) | K8: =IF(9<Supuestos!$D$26,0,IF(9-Supuestos!$D$26+1>=Supuestos!$D$29,Supuestos!$D$28,Supuestos!$D$27)) | L8: =IF(10<Supuestos!$D$26,0,IF(10-Supuestos!$D$26+1>=Supuestos!$D$29,Supuestos!$D$28,Supuestos!$D$27)) | M8: =IF(11<Supuestos!$D$26,0,IF(11-Supuestos!$D$26+1>=Supuestos!$D$29,Supuestos!$D$28,Supuestos!$D$27)) | N8: =IF(12<Supuestos!$D$26,0,IF(12-Supuestos!$D$26+1>=Supuestos!$D$29,Supuestos!$D$28,Supuestos!$D$27)) | O8: =IF(13<Supuestos!$D$26,0,IF(13-Supuestos!$D$26+1>=Supuestos!$D$29,Supuestos!$D$28,Supuestos!$D$27)) | P8: =IF(14<Supuestos!$D$26,0,IF(14-Supuestos!$D$26+1>=Supuestos!$D$29,Supuestos!$D$28,Supuestos!$D$27)) | Q8: =IF(15<Supuestos!$D$26,0,IF(15-Supuestos!$D$26+1>=Supuestos!$D$29,Supuestos!$D$28,Supuestos!$D$27))
A9: Ingresos por venta | B9: =B7*Supuestos!$B$13*B8 | C9: =C7*Supuestos!$B$13*C8 | D9: =D7*Supuestos!$B$13*D8 | E9: =E7*Supuestos!$B$13*E8 | F9: =F7*Supuestos!$B$13*F8 | G9: =G7*Supuestos!$B$13*G8 | H9: =H7*Supuestos!$B$13*H8 | I9: =I7*Supuestos!$B$13*I8 | ... Q9: =Q7*Supuestos!$B$13*Q8
A10: Caja por ventas (20% anticipado) | B10: =B9*(1-Supuestos!$D$38)+C9*Supuestos!$D$38 | C10: =C9*(1-Supuestos!$D$38)+D9*Supuestos!$D$38 | D10: =D9*(1-Supuestos!$D$38)+E9*Supuestos!$D$38 | E10: =E9*(1-Supuestos!$D$38)+F9*Supuestos!$D$38 | F10: =F9*(1-Supuestos!$D$38)+G9*Supuestos!$D$38 | G10: =G9*(1-Supuestos!$D$38)+H9*Supuestos!$D$38 | H10: =H9*(1-Supuestos!$D$38)+I9*Supuestos!$D$38 | I10: =I9*(1-Supuestos!$D$38)+J9*Supuestos!$D$38 | ... P10: =P9*(1-Supuestos!$D$38)+Q9*Supuestos!$D$38 | Q10: =Q9*(1-Supuestos!$D$38)
A12: Urbanización (4 macro-etapas) | B12: =Supuestos!$D$30*(IF(0=Supuestos!$D$26-1,0.3,0)+IF(0=Supuestos!$D$26,0.25,0)+IF(0=Supuestos!$D$26+2,0.25,0)+IF(0=Supuestos!$D$26+4,0.2,0)) | C12: =Supuestos!$D$30*(IF(1=Supuestos!$D$26-1,0.3,0)+IF(1=Supuestos!$D$26,0.25,0)+IF(1=Supuestos!$D$26+2,0.25,0)+IF(1=Supuestos!$D$26+4,0.2,0)) | D12: =Supuestos!$D$30*(IF(2=Supuestos!$D$26-1,0.3,0)+IF(2=Supuestos!$D$26,0.25,0)+IF(2=Supuestos!$D$26+2,0.25,0)+IF(2=Supuestos!$D$26+4,0.2,0)) | E12: =Supuestos!$D$30*(IF(3=Supuestos!$D$26-1,0.3,0)+IF(3=Supuestos!$D$26,0.25,0)+IF(3=Supuestos!$D$26+2,0.25,0)+IF(3=Supuestos!$D$26+4,0.2,0)) | F12: =Supuestos!$D$30*(IF(4=Supuestos!$D$26-1,0.3,0)+IF(4=Supuestos!$D$26,0.25,0)+IF(4=Supuestos!$D$26+2,0.25,0)+IF(4=Supuestos!$D$26+4,0.2,0)) | G12: =Supuestos!$D$30*(IF(5=Supuestos!$D$26-1,0.3,0)+IF(5=Supuestos!$D$26,0.25,0)+IF(5=Supuestos!$D$26+2,0.25,0)+IF(5=Supuestos!$D$26+4,0.2,0)) | H12: =Supuestos!$D$30*(IF(6=Supuestos!$D$26-1,0.3,0)+IF(6=Supuestos!$D$26,0.25,0)+IF(6=Supuestos!$D$26+2,0.25,0)+IF(6=Supuestos!$D$26+4,0.2,0)) | I12: =Supuestos!$D$30*(IF(7=Supuestos!$D$26-1,0.3,0)+IF(7=Supuestos!$D$26,0.25,0)+IF(7=Supuestos!$D$26+2,0.25,0)+IF(7=Supuestos!$D$26+4,0.2,0)) | J12: =Supuestos!$D$30*(IF(8=Supuestos!$D$26-1,0.3,0)+IF(8=Supuestos!$D$26,0.25,0)+IF(8=Supuestos!$D$26+2,0.25,0)+IF(8=Supuestos!$D$26+4,0.2,0)) | K12: =Supuestos!$D$30*(IF(9=Supuestos!$D$26-1,0.3,0)+IF(9=Supuestos!$D$26,0.25,0)+IF(9=Supuestos!$D$26+2,0.25,0)+IF(9=Supuestos!$D$26+4,0.2,0)) | L12: =Supuestos!$D$30*(IF(10=Supuestos!$D$26-1,0.3,0)+IF(10=Supuestos!$D$26,0.25,0)+IF(10=Supuestos!$D$26+2,0.25,0)+IF(10=Supuestos!$D$26+4,0.2,0)) | M12: =Supuestos!$D$30*(IF(11=Supuestos!$D$26-1,0.3,0)+IF(11=Supuestos!$D$26,0.25,0)+IF(11=Supuestos!$D$26+2,0.25,0)+IF(11=Supuestos!$D$26+4,0.2,0)) | N12: =Supuestos!$D$30*(IF(12=Supuestos!$D$26-1,0.3,0)+IF(12=Supuestos!$D$26,0.25,0)+IF(12=Supuestos!$D$26+2,0.25,0)+IF(12=Supuestos!$D$26+4,0.2,0)) | O12: =Supuestos!$D$30*(IF(13=Supuestos!$D$26-1,0.3,0)+IF(13=Supuestos!$D$26,0.25,0)+IF(13=Supuestos!$D$26+2,0.25,0)+IF(13=Supuestos!$D$26+4,0.2,0)) | P12: =Supuestos!$D$30*(IF(14=Supuestos!$D$26-1,0.3,0)+IF(14=Supuestos!$D$26,0.25,0)+IF(14=Supuestos!$D$26+2,0.25,0)+IF(14=Supuestos!$D$26+4,0.2,0)) | Q12: =Supuestos!$D$30*(IF(15=Supuestos!$D$26-1,0.3,0)+IF(15=Supuestos!$D$26,0.25,0)+IF(15=Supuestos!$D$26+2,0.25,0)+IF(15=Supuestos!$D$26+4,0.2,0))
A13: Proyectos, permisos y especialidades | B13: =Supuestos!$D$33 | C13: =Supuestos!$D$34 | D13: 0 | E13: 0 | F13: 0 | G13: 0 | H13: 0 | I13: 0 | J13: 0 | K13: 0 | L13: 0 | M13: 0 | N13: 0 | O13: 0 | P13: 0 | Q13: 0
A14: Gasto comercial | B14: =B9*Supuestos!$D$31 | C14: =C9*Supuestos!$D$31 | D14: =D9*Supuestos!$D$31 | E14: =E9*Supuestos!$D$31 | F14: =F9*Supuestos!$D$31 | G14: =G9*Supuestos!$D$31 | H14: =H9*Supuestos!$D$31 | I14: =I9*Supuestos!$D$31 | ... Q14: =Q9*Supuestos!$D$31
A15: Administración y contribuciones | B15: =IF(OR(B7>0,0<Supuestos!$D$26),Supuestos!$D$32+Supuestos!$D$35,0) | C15: =IF(OR(C7>0,1<Supuestos!$D$26),Supuestos!$D$32+Supuestos!$D$35,0) | D15: =IF(OR(D7>0,2<Supuestos!$D$26),Supuestos!$D$32+Supuestos!$D$35,0) | E15: =IF(OR(E7>0,3<Supuestos!$D$26),Supuestos!$D$32+Supuestos!$D$35,0) | F15: =IF(OR(F7>0,4<Supuestos!$D$26),Supuestos!$D$32+Supuestos!$D$35,0) | G15: =IF(OR(G7>0,5<Supuestos!$D$26),Supuestos!$D$32+Supuestos!$D$35,0) | H15: =IF(OR(H7>0,6<Supuestos!$D$26),Supuestos!$D$32+Supuestos!$D$35,0) | I15: =IF(OR(I7>0,7<Supuestos!$D$26),Supuestos!$D$32+Supuestos!$D$35,0) | J15: =IF(OR(J7>0,8<Supuestos!$D$26),Supuestos!$D$32+Supuestos!$D$35,0) | K15: =IF(OR(K7>0,9<Supuestos!$D$26),Supuestos!$D$32+Supuestos!$D$35,0) | L15: =IF(OR(L7>0,10<Supuestos!$D$26),Supuestos!$D$32+Supuestos!$D$35,0) | M15: =IF(OR(M7>0,11<Supuestos!$D$26),Supuestos!$D$32+Supuestos!$D$35,0) | N15: =IF(OR(N7>0,12<Supuestos!$D$26),Supuestos!$D$32+Supuestos!$D$35,0) | O15: =IF(OR(O7>0,13<Supuestos!$D$26),Supuestos!$D$32+Supuestos!$D$35,0) | P15: =IF(OR(P7>0,14<Supuestos!$D$26),Supuestos!$D$32+Supuestos!$D$35,0) | Q15: =IF(OR(Q7>0,15<Supuestos!$D$26),Supuestos!$D$32+Supuestos!$D$35,0)
A16: Total egresos operacionales | B16: =B12+B13+B14+B15 | C16: =C12+C13+C14+C15 | D16: =D12+D13+D14+D15 | E16: =E12+E13+E14+E15 | F16: =F12+F13+F14+F15 | G16: =G12+G13+G14+G15 | H16: =H12+H13+H14+H15 | I16: =I12+I13+I14+I15 | ... Q16: =Q12+Q13+Q14+Q15
A18: Pago del terreno | B18: =Supuestos!$B$18 | C18: =IF(1>=Supuestos!$B$20,MAX(0,Supuestos!$B$17-SUM($B18:B18)),MIN(C10*Supuestos!$B$19,MAX(0,Supuestos!$B$17-SUM($B18:B18)))) | D18: =IF(2>=Supuestos!$B$20,MAX(0,Supuestos!$B$17-SUM($B18:C18)),MIN(D10*Supuestos!$B$19,MAX(0,Supuestos!$B$17-SUM($B18:C18)))) | E18: =IF(3>=Supuestos!$B$20,MAX(0,Supuestos!$B$17-SUM($B18:D18)),MIN(E10*Supuestos!$B$19,MAX(0,Supuestos!$B$17-SUM($B18:D18)))) | F18: =IF(4>=Supuestos!$B$20,MAX(0,Supuestos!$B$17-SUM($B18:E18)),MIN(F10*Supuestos!$B$19,MAX(0,Supuestos!$B$17-SUM($B18:E18)))) | G18: =IF(5>=Supuestos!$B$20,MAX(0,Supuestos!$B$17-SUM($B18:F18)),MIN(G10*Supuestos!$B$19,MAX(0,Supuestos!$B$17-SUM($B18:F18)))) | H18: =IF(6>=Supuestos!$B$20,MAX(0,Supuestos!$B$17-SUM($B18:G18)),MIN(H10*Supuestos!$B$19,MAX(0,Supuestos!$B$17-SUM($B18:G18)))) | I18: =IF(7>=Supuestos!$B$20,MAX(0,Supuestos!$B$17-SUM($B18:H18)),MIN(I10*Supuestos!$B$19,MAX(0,Supuestos!$B$17-SUM($B18:H18)))) | J18: =IF(8>=Supuestos!$B$20,MAX(0,Supuestos!$B$17-SUM($B18:I18)),MIN(J10*Supuestos!$B$19,MAX(0,Supuestos!$B$17-SUM($B18:I18)))) | K18: =IF(9>=Supuestos!$B$20,MAX(0,Supuestos!$B$17-SUM($B18:J18)),MIN(K10*Supuestos!$B$19,MAX(0,Supuestos!$B$17-SUM($B18:J18)))) | L18: =IF(10>=Supuestos!$B$20,MAX(0,Supuestos!$B$17-SUM($B18:K18)),MIN(L10*Supuestos!$B$19,MAX(0,Supuestos!$B$17-SUM($B18:K18)))) | M18: =IF(11>=Supuestos!$B$20,MAX(0,Supuestos!$B$17-SUM($B18:L18)),MIN(M10*Supuestos!$B$19,MAX(0,Supuestos!$B$17-SUM($B18:L18)))) | N18: =IF(12>=Supuestos!$B$20,MAX(0,Supuestos!$B$17-SUM($B18:M18)),MIN(N10*Supuestos!$B$19,MAX(0,Supuestos!$B$17-SUM($B18:M18)))) | O18: =IF(13>=Supuestos!$B$20,MAX(0,Supuestos!$B$17-SUM($B18:N18)),MIN(O10*Supuestos!$B$19,MAX(0,Supuestos!$B$17-SUM($B18:N18)))) | P18: =IF(14>=Supuestos!$B$20,MAX(0,Supuestos!$B$17-SUM($B18:O18)),MIN(P10*Supuestos!$B$19,MAX(0,Supuestos!$B$17-SUM($B18:O18)))) | Q18: =IF(15>=Supuestos!$B$20,MAX(0,Supuestos!$B$17-SUM($B18:P18)),MIN(Q10*Supuestos!$B$19,MAX(0,Supuestos!$B$17-SUM($B18:P18))))
A19: Saldo del terreno pendiente | B19: =MAX(0,Supuestos!$B$17-SUM($B18:B18)) | C19: =MAX(0,Supuestos!$B$17-SUM($B18:C18)) | D19: =MAX(0,Supuestos!$B$17-SUM($B18:D18)) | E19: =MAX(0,Supuestos!$B$17-SUM($B18:E18)) | F19: =MAX(0,Supuestos!$B$17-SUM($B18:F18)) | G19: =MAX(0,Supuestos!$B$17-SUM($B18:G18)) | H19: =MAX(0,Supuestos!$B$17-SUM($B18:H18)) | I19: =MAX(0,Supuestos!$B$17-SUM($B18:I18)) | ... Q19: =MAX(0,Supuestos!$B$17-SUM($B18:Q18))
A20: Impuesto a la renta (pagado al año siguiente) | B20: 0 | C20: =MAX(0,(B9-B16-B7*Supuestos!$B$17*0.881/Supuestos!$B$7)*Supuestos!$D$36) | D20: =MAX(0,(C9-C16-C7*Supuestos!$B$17*0.881/Supuestos!$B$7)*Supuestos!$D$36) | E20: =MAX(0,(D9-D16-D7*Supuestos!$B$17*0.881/Supuestos!$B$7)*Supuestos!$D$36) | F20: =MAX(0,(E9-E16-E7*Supuestos!$B$17*0.881/Supuestos!$B$7)*Supuestos!$D$36) | G20: =MAX(0,(F9-F16-F7*Supuestos!$B$17*0.881/Supuestos!$B$7)*Supuestos!$D$36) | H20: =MAX(0,(G9-G16-G7*Supuestos!$B$17*0.881/Supuestos!$B$7)*Supuestos!$D$36) | I20: =MAX(0,(H9-H16-H7*Supuestos!$B$17*0.881/Supuestos!$B$7)*Supuestos!$D$36) | J20: =MAX(0,(I9-I16-I7*Supuestos!$B$17*0.881/Supuestos!$B$7)*Supuestos!$D$36) | ... Q20: =MAX(0,(P9-P16-P7*Supuestos!$B$17*0.881/Supuestos!$B$7)*Supuestos!$D$36)
A22: FLUJO DE CAJA DEL PERÍODO | B22: =B10-B16-B18-B20 | C22: =C10-C16-C18-C20 | D22: =D10-D16-D18-D20 | E22: =E10-E16-E18-E20 | F22: =F10-F16-F18-F20 | G22: =G10-G16-G18-G20 | H22: =H10-H16-H18-H20 | I22: =I10-I16-I18-I20 | ... Q22: =Q10-Q16-Q18-Q20
A23: Flujo acumulado | B23: =B22 | C23: =B23+C22 | D23: =C23+D22 | E23: =D23+E22 | F23: =E23+F22 | G23: =F23+G22 | H23: =G23+H22 | I23: =H23+I22 | J23: =I23+J22 | ... Q23: =P23+Q22
A25: INDICADORES
A26: Ingresos totales | B26: =SUM(B9:Q9)
A27: Costos totales (con terreno) | B27: =SUM(B16:Q16)+Supuestos!$B$17*0.881
A28: Utilidad antes de impuesto | B28: =B26-B27
A29: Margen bruto | B29: =B28/B26
A30: Impuesto | B30: =B28*Supuestos!$D$36
A31: Utilidad neta | B31: =B28-B30
A32: Margen neto | B32: =B31/B26
A33: Capital máximo expuesto | B33: =-MIN(B23:Q23,0)
A34: TIR del proyecto | B34: =IRR(B22:Q22)
A35: VAN a la tasa de descuento | B35: =NPV(Supuestos!$D$37,C22:Q22)+B22
A36: Precio promedio logrado (UF/m²) | B36: =B26/Supuestos!$B$6
A37: Saldo impago al vencer el plazo | B37: =INDEX(B19:Q19,Supuestos!$B$20+1)

Sheet Etapas 2 y 3
A1: ACTIVOS DE RENTA — STRIP CENTER, COLEGIO Y ESTACIÓN DE SERVICIO
A3: ETAPA 2 — STRIP CENTER (terreno 4.386 m²)
A4: Variable | B4: Conservador | C4: Base | D4: Optimista | E4: Comentario
A5: Superficie arrendable (m²) | B5: 619.2 | C5: 619.2 | D5: 619.2 | E5: L_05: 8 locales de 38,4 + 2 restaurantes de 156
A6: Superficie construida total (m²) | B6: 729.7 | C6: 729.7 | D6: 729.7 | E6: Incluye administración y baños/camarines
A7: Renta (UF/m²/mes) | B7: 0.28 | C7: 0.35 | D7: 0.42 | E7: Referencia RM: 0,69 en primer piso
A8: NOI de 4 canchas de pádel (UF/año) | B8: 500 | C8: 900 | D8: 1350 | E8: Arrendadas a operador, sin operar
A9: Inversión en canchas de pádel (UF) | B9: 4200 | C9: 3500 | D9: 3200 | E9: 4 canchas, cierres e iluminación
A10: Vacancia | B10: 0.15 | C10: 0.08 | D10: 0.05
A11: Costo de construcción (UF/m²) | B11: 27 | C11: 24 | D11: 22 | E11: Shell & core
A12: Obras exteriores y empalmes (UF) | B12: 4500 | C12: 4500 | D12: 4500 | E12: Estacionamientos, paisajismo
A13: Costos blandos | B13: 0.1 | C13: 0.1 | D13: 0.1 | E13: Proyectos, permisos, gerencia
A14: Terreno asignado (UF) | B14: 2710 | C14: 2710 | D14: 2710 | E14: 2,3% de las 119.000 UF
A15: Gastos no recuperables | B15: 0.12 | C15: 0.12 | D15: 0.12 | E15: Contribuciones, administración
A16: Cap rate de salida | B16: 0.095 | C16: 0.085 | D16: 0.075 | E16: Chile 5,8–7,5%; premio regional
A17: Inversión total (UF) | B17: =B6*B11*(1+B13)+B9+B12+B14 | C17: =C6*C11*(1+C13)+C9+C12+C14 | D17: =D6*D11*(1+D13)+D9+D12+D14
A18: Renta bruta anual (UF) | B18: =B5*B7*12 | C18: =C5*C7*12 | D18: =D5*D7*12
A19: NOI anual (UF) | B19: =B18*(1-B10)*(1-B15)+B8 | C19: =C18*(1-C10)*(1-C15)+C8 | D19: =D18*(1-D10)*(1-D15)+D8
A20: Yield on cost | B20: =B19/B17 | C20: =C19/C17 | D20: =D19/D17
A21: Valor estabilizado (UF) | B21: =B19/B16 | C21: =C19/C16 | D21: =D19/D16
A22: Creación de valor (UF) | B22: =B21-B17 | C22: =C21-C17 | D22: =D21-D17
A23: Payback (años) | B23: =B17/B19 | C23: =C17/C19 | D23: =D17/D19
A26: ETAPA 3 — COMPARACIÓN DE ALTERNATIVAS PARA EL PAÑO NORTE (18.619 m²)
B27: Colegio build-to-suit | C27: Venta del paño | D27: EDS arrendada | E27: Comentario
A28: Inversión propia (UF) | B28: 177894 | C28: 0 | D28: 4879 | E28: Colegio L_09: 3.849 m² cerrados + 2.088 patio techado
A29: Flujo anual (UF) | B29: 12286 | C29: 0 | D29: 4200 | E29: EDS: canon de 350 UF/mes
A30: Rentabilidad sobre costo | B30: 0.069 | C30: 0 | D30: 0.861
A31: Valor del activo (UF) | B31: 144541 | C31: 45885 | D31: 56000 | E31: Venta del paño a 2,5 UF/m²
A32: Creación de valor (UF) | B32: -33352 | C32: 34383 | D32: 51121 | E32: El colegio destruye valor en escenario Base
A33: Payback (años) | B33: 14.5 | C33: 0 | D33: 1.2
A34: Superficie que ocupa (m²) | B34: 18354 | C34: 18354 | D34: 2200 | E34: La EDS deja 16.154 m² libres
A36: Requisito duro para la EDS: TMDA de Av. San Miguel sobre 8.000–12.000 veh/día para atraer a un operador de marca. Verificar en Dirección de Vialidad del Maule.
